Workbook

Sheet Suppliers
A1: Golden ID | B1: Supplier | C1: Country | D1: Commodity | E1: Segment (M2) | F1: Spend (EUR) | G1: OTD % | H1: PPM | I1: Payment term | J1: Spend share | K1: Cumulative share | L1: ABC class | M1: Net days | N1: Cash effect (EUR) | O1: Discount (EUR)
A2: G0098 | B2: KAPPATEC GMBH | C2: AT | D2: Plastic housings | E2: Strategic and reliable | F2: 8729465 | G2: 87 | H2: 117 | I2: NT60 | J2: =F2/SUM($F$2:$F$121) -> 0.029880261 | K2: =SUM($J$2:J2) -> 0.029880261 | L2: =IF(K2<=80%,"A",IF(K2<=95%,"B","C")) -> A | M2: =_xlfn.XLOOKUP(I2,Terms!A:A,Terms!C:C,"") -> 60 | N2: =IF(M2="",0,MAX(0,Settings!$B$5-M2)*F2/Settings!$B$4) -> 0 | O2: =F2*_xlfn.XLOOKUP(I2,Terms!A:A,Terms!D:D,0) -> 0
A3: G0016 | B3: Lumencast GmbH | C3: AT | D3: Packaging | E3: Quality risk | F3: 8166335 | G3: 94.9 | H3: 699 | I3: missing | J3: =F3/SUM($F$2:$F$121) -> 0.027952712 | K3: =SUM($J$2:J3) -> 0.057832974 | L3: =IF(K3<=80%,"A",IF(K3<=95%,"B","C")) -> A | M3: =_xlfn.XLOOKUP(I3,Terms!A:A,Terms!C:C,"") | N3: =IF(M3="",0,MAX(0,Settings!$B$5-M3)*F3/Settings!$B$4) -> 0 | O3: =F3*_xlfn.XLOOKUP(I3,Terms!A:A,Terms!D:D,0) -> 0
A4: G0102 | B4: Deltaarts SAS | C4: FR | D4: Valves | E4: Strategic and reliable | F4: 7892755 | G4: 93.3 | H4: 134 | I4: NT30 | J4: =F4/SUM($F$2:$F$121) -> 0.02701627 | K4: =SUM($J$2:J4) -> 0.084849243 | L4: =IF(K4<=80%,"A",IF(K4<=95%,"B","C")) -> A | M4: =_xlfn.XLOOKUP(I4,Terms!A:A,Terms!C:C,"") -> 30 | N4: =IF(M4="",0,MAX(0,Settings!$B$5-M4)*F4/Settings!$B$4) -> 928559.41 | O4: =F4*_xlfn.XLOOKUP(I4,Terms!A:A,Terms!D:D,0) -> 0
A5: G0052 | B5: Krafttec GmbH | C5: DE | D5: Plastic housings | E5: Quality risk | F5: 7297508 | G5: 85.1 | H5: 789 | I5: NT60 | J5: =F5/SUM($F$2:$F$121) -> 0.024978787 | K5: =SUM($J$2:J5) -> 0.10982803 | L5: =IF(K5<=80%,"A",IF(K5<=95%,"B","C")) -> A | M5: =_xlfn.XLOOKUP(I5,Terms!A:A,Terms!C:C,"") -> 60 | N5: =IF(M5="",0,MAX(0,Settings!$B$5-M5)*F5/Settings!$B$4) -> 0 | O5: =F5*_xlfn.XLOOKUP(I5,Terms!A:A,Terms!D:D,0) -> 0
A6: G0012 | B6: Velawerk s.r.o. | C6: CZ | D6: Plastic housings | E6: Strategic and reliable | F6: 7016505 | G6: 96.3 | H6: 102 | I6: NT45 | J6: =F6/SUM($F$2:$F$121) -> 0.024016936 | K6: =SUM($J$2:J6) -> 0.13384497 | L6: =IF(K6<=80%,"A",IF(K6<=95%,"B","C")) -> A | M6: =_xlfn.XLOOKUP(I6,Terms!A:A,Terms!C:C,"") -> 45 | N6: =IF(M6="",0,MAX(0,Settings!$B$5-M6)*F6/Settings!$B$4) -> 412735.59 | O6: =F6*_xlfn.XLOOKUP(I6,Terms!A:A,Terms!D:D,0) -> 0
A7: G0083 | B7: Kappawerk GmbH | C7: DE | D7: Packaging | E7: Strategic and reliable | F7: 6591040 | G7: 92.4 | H7: 117 | I7: NT30 | J7: =F7/SUM($F$2:$F$121) -> 0.022560603 | K7: =SUM($J$2:J7) -> 0.15640557 | L7: =IF(K7<=80%,"A",IF(K7<=95%,"B","C")) -> A | M7: =_xlfn.XLOOKUP(I7,Terms!A:A,Terms!C:C,"") -> 30 | N7: =IF(M7="",0,MAX(0,Settings!$B$5-M7)*F7/Settings!$B$4) -> 775416.47 | O7: =F7*_xlfn.XLOOKUP(I7,Terms!A:A,Terms!D:D,0) -> 0
A8: G0103 | B8: TAUROGUSS GMBH | C8: DE | D8: Rubber seals | E8: Strategic and reliable | F8: 6508860 | G8: 88.2 | H8: 60 | I8: SK14 | J8: =F8/SUM($F$2:$F$121) -> 0.022279308 | K8: =SUM($J$2:J8) -> 0.17868488 | L8: =IF(K8<=80%,"A",IF(K8<=95%,"B","C")) -> A | M8: =_xlfn.XLOOKUP(I8,Terms!A:A,Terms!C:C,"") -> 30 | N8: =IF(M8="",0,MAX(0,Settings!$B$5-M8)*F8/Settings!$B$4) -> 765748.24 | O8: =F8*_xlfn.XLOOKUP(I8,Terms!A:A,Terms!D:D,0) -> 130177.2
A9: G0044 | B9: Ventoplast GmbH | C9: DE | D9: Electronic sensors | E9: Critical: quality and delivery | F9: 6491982 | G9: 58.8 | H9: 911 | I9: NT60 | J9: =F9/SUM($F$2:$F$121) -> 0.022221536 | K9: =SUM($J$2:J9) -> 0.20090641 | L9: =IF(K9<=80%,"A",IF(K9<=95%,"B","C")) -> A | M9: =_xlfn.XLOOKUP(I9,Terms!A:A,Terms!C:C,"") -> 60 | N9: =IF(M9="",0,MAX(0,Settings!$B$5-M9)*F9/Settings!$B$4) -> 0 | O9: =F9*_xlfn.XLOOKUP(I9,Terms!A:A,Terms!D:D,0) -> 0
A10: G0063 | B10: Polarcast Sp. z o.o. | C10: PL | D10: Valves | E10: Critical: quality and delivery | F10: 6425100 | G10: 79.3 | H10: 5265 | I10: NT45 | J10: =F10/SUM($F$2:$F$121) -> 0.021992604 | K10: =SUM($J$2:J10) -> 0.22289902 | L10: =IF(K10<=80%,"A",IF(K10<=95%,"B","C")) -> A | M10: =_xlfn.XLOOKUP(I10,Terms!A:A,Terms!C:C,"") -> 45 | N10: =IF(M10="",0,MAX(0,Settings!$B$5-M10)*F10/Settings!$B$4) -> 377947.06 | O10: =F10*_xlfn.XLOOKUP(I10,Terms!A:A,Terms!D:D,0) -> 0
A11: G0094 | B11: Cerroparts | C11: DE | D11: Packaging | E11: Strategic and reliable | F11: 6072516 | G11: 96.5 | H11: 104 | I11: NT60 | J11: =F11/SUM($F$2:$F$121) -> 0.020785737 | K11: =SUM($J$2:J11) -> 0.24368475 | L11: =IF(K11<=80%,"A",IF(K11<=95%,"B","C")) -> A | M11: =_xlfn.XLOOKUP(I11,Terms!A:A,Terms!C:C,"") -> 60 | N11: =IF(M11="",0,MAX(0,Settings!$B$5-M11)*F11/Settings!$B$4) -> 0 | O11: =F11*_xlfn.XLOOKUP(I11,Terms!A:A,Terms!D:D,0) -> 0
A12: G0077 | B12: Orbisparts GmbH | C12: DE | D12: Hoses & connectors | E12: Critical: quality and delivery | F12: 5969282 | G12: 64.1 | H12: 916 | I12: NT45 | J12: =F12/SUM($F$2:$F$121) -> 0.020432375 | K12: =SUM($J$2:J12) -> 0.26411713 | L12: =IF(K12<=80%,"A",IF(K12<=95%,"B","C")) -> A | M12: =_xlfn.XLOOKUP(I12,Terms!A:A,Terms!C:C,"") -> 45 | N12: =IF(M12="",0,MAX(0,Settings!$B$5-M12)*F12/Settings!$B$4) -> 351134.24 | O12: =F12*_xlfn.XLOOKUP(I12,Terms!A:A,Terms!D:D,0) -> 0
A13: G0117 | B13: Deltaflex Sp. z o.o. | C13: PL | D13: Aluminium castings | E13: Delivery risk | F13: 5915328 | G13: 51.6 | H13: 114 | I13: NT60 | J13: =F13/SUM($F$2:$F$121) -> 0.020247695 | K13: =SUM($J$2:J13) -> 0.28436482 | L13: =IF(K13<=80%,"A",IF(K13<=95%,"B","C")) -> A | M13: =_xlfn.XLOOKUP(I13,Terms!A:A,Terms!C:C,"") -> 60 | N13: =IF(M13="",0,MAX(0,Settings!$B$5-M13)*F13/Settings!$B$4) -> 0 | O13: =F13*_xlfn.XLOOKUP(I13,Terms!A:A,Terms!D:D,0) -> 0
... A121: G0075 | B121: Silberguss GmbH | C121: DE | D121: Valves | E121: Reliable, lower spend | F121: 271699 | G121: 100 | H121: 192 | I121: NT30 | J121: =F121/SUM($F$2:$F$121) -> 0.00093000397 | K121: =SUM($J$2:J121) -> 1 | L121: =IF(K121<=80%,"A",IF(K121<=95%,"B","C")) -> C | M121: =_xlfn.XLOOKUP(I121,Terms!A:A,Terms!C:C,"") -> 30 | N121: =IF(M121="",0,MAX(0,Settings!$B$5-M121)*F121/Settings!$B$4) -> 31964.588 | O121: =F121*_xlfn.XLOOKUP(I121,Terms!A:A,Terms!D:D,0) -> 0

Sheet Results
A1: Class | B1: Suppliers | D1: Row Labels | E1: Sum of Spend (EUR) | F1: Sum of Spend (EUR)2
A2: A | B2: =COUNTIF(Suppliers!L:L,A2) -> 60 | D2: Critical: quality and delivery | E2: 75367089 | F2: 0.25797552
A3: B | B3: =COUNTIF(Suppliers!L:L,A3) -> 34 | D3: Delivery risk | E3: 60047233 | F3: 0.20553688
A4: C | B4: =COUNTIF(Suppliers!L:L,A4) -> 26 | D4: Quality risk | E4: 50718474 | F4: 0.17360528
A5: Total | B5: =SUM(B2:B4) -> 120 | D5: Reliable, lower spend | E5: 15541762 | F5: 0.05319821
D6: Strategic and reliable | E6: 90473657 | F6: 0.3096841
D7: Grand Total | E7: 292148215 | F7: 1
A8: Cash effect, 60-day terms (EUR) | B8: =SUM(Suppliers!N:N) -> 18039476
A9: Cash discount potential (EUR) | B9: =SUM(Suppliers!O:O) -> 1154389.6
A10: Suppliers without payment terms | B10: =COUNTIF(Suppliers!I:I,"missing") -> 4
A11: Spend without payment terms (EUR) | B11: =SUMIF(Suppliers!I:I,"missing",Suppliers!F:F) -> 12687450

Sheet Terms
A1: Code | B1: Description | C1: Net days | D1: Cash discount % | E1: Discount days
A2: NT30 | B2: Net 30 | C2: 30 | D2: 0 | E2: 0
A3: NT45 | B3: 45 days | C3: 45 | D3: 0 | E3: 0
A4: NT60 | B4: 60 days net | C4: 60 | D4: 0 | E4: 0
A5: SK14 | B5: 2% 14 days, net 30 | C5: 30 | D5: 0.02 | E5: 14

Sheet Settings
A1: Setting | B1: Value | C1: Note
A2: Data period: first delivery | B2: 46027 | C2: Spend in this workbook covers this period only
A3: Data period: last delivery | B3: 46281
A4: Days in data period | B4: 255 | C4: Used to turn spend into spend per day
A5: Target payment term (days) | B5: 60 | C5: Assumption: company standard term
A7: All data is synthetic. Spend = quantity received x unit price from the purchase-order lines.
